cartiflette/__init__.py
cartiflette/client.py
cartiflette/config.py
cartiflette/constants.py
cartiflette/utils.py
cartiflette-0.1.6.dist-info/METADATA
cartiflette-0.1.6.dist-info/WHEEL
cartiflette-0.1.6.dist-info/RECORD
