Metadata-Version: 2.1
Name: cartiflette
Version: 0.1.6
Summary: Tools to easily retrieve French borders for geographic data analytics
License: OPEN LICENCE 2.0/LICENCE OUVERTE 2.0
Author: Lino Galiana
Author-email: lino.galiana@insee.fr
Requires-Python: >=3.9,<4.0
Classifier: License :: Other/Proprietary License
Classifier: Programming Language :: Python :: 3
Classifier: Programming Language :: Python :: 3.9
Classifier: Programming Language :: Python :: 3.10
Classifier: Programming Language :: Python :: 3.11
Classifier: Programming Language :: Python :: 3.12
Classifier: Programming Language :: Python :: 3.13
Requires-Dist: geopandas (>=1.0.1,<2.0.0)
Requires-Dist: platformdirs (>=4.3.6,<5.0.0)
Requires-Dist: requests (>=2.32.3,<3.0.0)
Requires-Dist: requests-cache (>=1.2.1,<2.0.0)
